<?xml version="1.0"?>


<!--                                                                         -->
<!-- Generated by IntelliAsnCC ASN.1 compiler (C, C++, Java).                -->
<!--                                                                         -->
<!-- Do not edit!                                                            -->
<!--                                                                         -->
<!--                                                                         -->
<!-- (C) 2000, 2001 IntelliNet Technologies Inc. All Rights Reserved.        -->
<!--                                                                         -->
<!--                                                                         -->


<asnType>

<asnSequenceOf>

<className>EstablishTemporaryConnectionArg::Extensions</className>
<asnTypeName>EstablishTemporaryConnectionArg::extensions</asnTypeName>
<moduleName>INAP_CS2</moduleName>


<memberFunctions>

<memberFunctionAdd>
<name>AddElement</name>
<signature>void AddElement(ExtensionField* element)</signature>
<elementTypeName>ExtensionField</elementTypeName>
</memberFunctionAdd>

<memberFunctionAddWithRef>
<name>AddElement</name>
<signature>void AddElement(const ExtensionField&amp; element)</signature>
<elementTypeName>ExtensionField</elementTypeName>
</memberFunctionAddWithRef>

<memberFunctionAt>
<name>ElementAt</name>
<signature>const ExtensionField&amp; ElementAt(size_t index) const</signature>
<elementTypeName>ExtensionField</elementTypeName>
</memberFunctionAt>

</memberFunctions>



<asnDefinition>

<line>
<text></text>
</line>
<line>
<text>-- EstablishTemporaryConnectionArg information: </text>
</line>
<line>
<text>-- [not recursive]</text>
</line>
<line>
<text>-- [not exported]</text>
</line>
<line>
<text>-- [local reference counter = 0]</text>
</line>
<line>
<text>-- [import reference counter = 0]</text>
</line>
<line>
<text></text>
</line>
<line>
<text>EstablishTemporaryConnectionArg ::= SEQUENCE</text>
</line>
<line>
<text>{</text>
</line>
<line>
<text>    assistingSSPIPRoutingAddress [0] IMPLICIT AssistingSSPIPRoutingAddress -- [linked] --,</text>
<shift></shift>
</line>
<line>
<text></text>
</line>
<line>
<text>    correlationID [1] IMPLICIT CorrelationID -- [linked] -- OPTIONAL,</text>
<shift></shift>
</line>
<line>
<text></text>
</line>
<line>
<text>    partyToConnect CHOICE</text>
<shift></shift>
</line>
<line>
<text>    {</text>
<shift></shift>
</line>
<line>
<text>        legID [2] IMPLICIT LegID -- [linked] --,</text>
<shift></shift>
<shift></shift>
</line>
<line>
<text></text>
</line>
<line>
<text>        callSegmentID [7] IMPLICIT CallSegmentID -- [linked] --</text>
<shift></shift>
<shift></shift>
</line>
<line>
<text>    } OPTIONAL,</text>
<shift></shift>
</line>
<line>
<text></text>
</line>
<line>
<text>    scfID [3] IMPLICIT ScfID -- [linked] -- OPTIONAL,</text>
<shift></shift>
</line>
<line>
<text></text>
</line>
<line>
<text>    extensions [4] IMPLICIT SEQUENCE (SIZE(1..numOfExtensions -- [linked] --)) OF ExtensionField -- [linked] -- OPTIONAL,</text>
<shift></shift>
</line>
<line>
<text></text>
</line>
<line>
<text>    carrier [5] IMPLICIT Carrier -- [linked] -- OPTIONAL,</text>
<shift></shift>
</line>
<line>
<text></text>
</line>
<line>
<text>    serviceInteractionIndicators [30] IMPLICIT ServiceInteractionIndicators -- [linked] -- OPTIONAL,</text>
<shift></shift>
</line>
<line>
<text></text>
</line>
<line>
<text>    serviceInteractionIndicatorsTwo [6] IMPLICIT ServiceInteractionIndicatorsTwo -- [linked] -- OPTIONAL</text>
<shift></shift>
</line>
<line>
<text>}</text>
</line>
<line>
<text></text>
</line>
<line>
<text></text>
</line>

</asnDefinition>



</asnSequenceOf>

</asnType>

