<?xml version="1.0"?>


<!--                                                                         -->
<!-- Generated by IntelliAsnCC ASN.1 compiler (C, C++, Java).                -->
<!--                                                                         -->
<!-- Do not edit!                                                            -->
<!--                                                                         -->
<!--                                                                         -->
<!-- (C) 2000, 2001 IntelliNet Technologies Inc. All Rights Reserved.        -->
<!--                                                                         -->
<!--                                                                         -->


<asnType>

<asnSequence>

<className>ForwardingData</className>
<asnTypeName>ForwardingData</asnTypeName>
<moduleName>MAP_V9</moduleName>


<memberFunctions>

<memberFunctionSet>
<name>SetForwardedToNumber</name>
<signature>void SetForwardedToNumber(ISDN_AddressString* element)</signature>
<elmentName>ForwardedToNumber</elmentName>
<asnElementName>forwardedToNumber</asnElementName>
<elementTypeName>ISDN_AddressString</elementTypeName>
<optional>yes</optional>
</memberFunctionSet>

<memberFunctionSetWithRef>
<name>SetForwardedToNumber</name>
<signature>void SetForwardedToNumber(const ISDN_AddressString&amp; element)</signature>
<elementName>ForwardedToNumber</elementName>
<asnElementName>forwardedToNumber</asnElementName>
<elementTypeName>ISDN_AddressString</elementTypeName>
<optional>yes</optional>
</memberFunctionSetWithRef>

<memberFunctionGet>
<name>GetForwardedToNumber</name>
<signature>const ISDN_AddressString&amp; GetForwardedToNumber() const</signature>
<elementName>ForwardedToNumber</elementName>
<asnElementName>forwardedToNumber</asnElementName>
<elementTypeName>ISDN_AddressString</elementTypeName>
<optional>yes</optional>
</memberFunctionGet>

<memberFunctionOption>
<name>OptionForwardedToNumber</name>
<signature>bool OptionForwardedToNumber() const</signature>
<elementName>ForwardedToNumber</elementName>
<asnElementName>forwardedToNumber</asnElementName>
<elementTypeName>ISDN_AddressString</elementTypeName>
</memberFunctionOption>

<memberFunctionSet>
<name>SetForwardedToSubaddress</name>
<signature>void SetForwardedToSubaddress(ISDN_SubaddressString* element)</signature>
<elmentName>ForwardedToSubaddress</elmentName>
<asnElementName>forwardedToSubaddress</asnElementName>
<elementTypeName>ISDN_SubaddressString</elementTypeName>
<optional>yes</optional>
</memberFunctionSet>

<memberFunctionSetWithRef>
<name>SetForwardedToSubaddress</name>
<signature>void SetForwardedToSubaddress(const ISDN_SubaddressString&amp; element)</signature>
<elementName>ForwardedToSubaddress</elementName>
<asnElementName>forwardedToSubaddress</asnElementName>
<elementTypeName>ISDN_SubaddressString</elementTypeName>
<optional>yes</optional>
</memberFunctionSetWithRef>

<memberFunctionGet>
<name>GetForwardedToSubaddress</name>
<signature>const ISDN_SubaddressString&amp; GetForwardedToSubaddress() const</signature>
<elementName>ForwardedToSubaddress</elementName>
<asnElementName>forwardedToSubaddress</asnElementName>
<elementTypeName>ISDN_SubaddressString</elementTypeName>
<optional>yes</optional>
</memberFunctionGet>

<memberFunctionOption>
<name>OptionForwardedToSubaddress</name>
<signature>bool OptionForwardedToSubaddress() const</signature>
<elementName>ForwardedToSubaddress</elementName>
<asnElementName>forwardedToSubaddress</asnElementName>
<elementTypeName>ISDN_SubaddressString</elementTypeName>
</memberFunctionOption>

<memberFunctionSet>
<name>SetForwardingOptions</name>
<signature>void SetForwardingOptions(ForwardingOptions* element)</signature>
<elmentName>ForwardingOptions</elmentName>
<asnElementName>forwardingOptions</asnElementName>
<elementTypeName>ForwardingOptions</elementTypeName>
<optional>yes</optional>
</memberFunctionSet>

<memberFunctionSetWithRef>
<name>SetForwardingOptions</name>
<signature>void SetForwardingOptions(const ForwardingOptions&amp; element)</signature>
<elementName>ForwardingOptions</elementName>
<asnElementName>forwardingOptions</asnElementName>
<elementTypeName>ForwardingOptions</elementTypeName>
<optional>yes</optional>
</memberFunctionSetWithRef>

<memberFunctionGet>
<name>GetForwardingOptions</name>
<signature>const ForwardingOptions&amp; GetForwardingOptions() const</signature>
<elementName>ForwardingOptions</elementName>
<asnElementName>forwardingOptions</asnElementName>
<elementTypeName>ForwardingOptions</elementTypeName>
<optional>yes</optional>
</memberFunctionGet>

<memberFunctionOption>
<name>OptionForwardingOptions</name>
<signature>bool OptionForwardingOptions() const</signature>
<elementName>ForwardingOptions</elementName>
<asnElementName>forwardingOptions</asnElementName>
<elementTypeName>ForwardingOptions</elementTypeName>
</memberFunctionOption>

<memberFunctionSet>
<name>SetExtensionContainer</name>
<signature>void SetExtensionContainer(ExtensionContainer* element)</signature>
<elmentName>ExtensionContainer</elmentName>
<asnElementName>extensionContainer</asnElementName>
<elementTypeName>ExtensionContainer</elementTypeName>
<optional>yes</optional>
</memberFunctionSet>

<memberFunctionSetWithRef>
<name>SetExtensionContainer</name>
<signature>void SetExtensionContainer(const ExtensionContainer&amp; element)</signature>
<elementName>ExtensionContainer</elementName>
<asnElementName>extensionContainer</asnElementName>
<elementTypeName>ExtensionContainer</elementTypeName>
<optional>yes</optional>
</memberFunctionSetWithRef>

<memberFunctionGet>
<name>GetExtensionContainer</name>
<signature>const ExtensionContainer&amp; GetExtensionContainer() const</signature>
<elementName>ExtensionContainer</elementName>
<asnElementName>extensionContainer</asnElementName>
<elementTypeName>ExtensionContainer</elementTypeName>
<optional>yes</optional>
</memberFunctionGet>

<memberFunctionOption>
<name>OptionExtensionContainer</name>
<signature>bool OptionExtensionContainer() const</signature>
<elementName>ExtensionContainer</elementName>
<asnElementName>extensionContainer</asnElementName>
<elementTypeName>ExtensionContainer</elementTypeName>
</memberFunctionOption>

<memberFunctionSet>
<name>SetLongForwardedToNumber</name>
<signature>void SetLongForwardedToNumber(FTN_AddressString* element)</signature>
<elmentName>LongForwardedToNumber</elmentName>
<asnElementName>longForwardedToNumber</asnElementName>
<elementTypeName>FTN_AddressString</elementTypeName>
<optional>yes</optional>
</memberFunctionSet>

<memberFunctionSetWithRef>
<name>SetLongForwardedToNumber</name>
<signature>void SetLongForwardedToNumber(const FTN_AddressString&amp; element)</signature>
<elementName>LongForwardedToNumber</elementName>
<asnElementName>longForwardedToNumber</asnElementName>
<elementTypeName>FTN_AddressString</elementTypeName>
<optional>yes</optional>
</memberFunctionSetWithRef>

<memberFunctionGet>
<name>GetLongForwardedToNumber</name>
<signature>const FTN_AddressString&amp; GetLongForwardedToNumber() const</signature>
<elementName>LongForwardedToNumber</elementName>
<asnElementName>longForwardedToNumber</asnElementName>
<elementTypeName>FTN_AddressString</elementTypeName>
<optional>yes</optional>
</memberFunctionGet>

<memberFunctionOption>
<name>OptionLongForwardedToNumber</name>
<signature>bool OptionLongForwardedToNumber() const</signature>
<elementName>LongForwardedToNumber</elementName>
<asnElementName>longForwardedToNumber</asnElementName>
<elementTypeName>FTN_AddressString</elementTypeName>
</memberFunctionOption>

</memberFunctions>



<asnDefinition>

<line>
<text></text>
</line>
<line>
<text>-- ForwardingData information: </text>
</line>
<line>
<text>-- [not recursive]</text>
</line>
<line>
<text>-- [not exported]</text>
</line>
<line>
<text>-- [local reference counter = 4]</text>
</line>
<line>
<text>-- [import reference counter = 0]</text>
</line>
<line>
<text></text>
</line>
<line>
<text>ForwardingData ::= SEQUENCE</text>
</line>
<line>
<text>{</text>
</line>
<line>
<text>    forwardedToNumber [5] IMPLICIT ISDN-AddressString -- [linked] -- OPTIONAL,</text>
<shift></shift>
</line>
<line>
<text></text>
</line>
<line>
<text>    forwardedToSubaddress [4] IMPLICIT ISDN-SubaddressString -- [linked] -- OPTIONAL,</text>
<shift></shift>
</line>
<line>
<text></text>
</line>
<line>
<text>    forwardingOptions [6] IMPLICIT ForwardingOptions -- [linked] -- OPTIONAL,</text>
<shift></shift>
</line>
<line>
<text></text>
</line>
<line>
<text>    extensionContainer [7] IMPLICIT ExtensionContainer -- [linked] -- OPTIONAL,</text>
<shift></shift>
</line>
<line>
<text></text>
</line>
<line>
<text>    longForwardedToNumber [8] IMPLICIT FTN-AddressString -- [linked] -- OPTIONAL</text>
<shift></shift>
</line>
<line>
<text>}</text>
</line>
<line>
<text></text>
</line>
<line>
<text></text>
</line>

</asnDefinition>



</asnSequence>

</asnType>

