<?xml version="1.0"?>


<!--                                                                         -->
<!-- Generated by IntelliAsnCC ASN.1 compiler (C, C++, Java).                -->
<!--                                                                         -->
<!-- Do not edit!                                                            -->
<!--                                                                         -->
<!--                                                                         -->
<!-- (C) 2000, 2001 IntelliNet Technologies Inc. All Rights Reserved.        -->
<!--                                                                         -->
<!--                                                                         -->


<asnType>

<asnChoice>

<className>GPRSSubscriptionDataWithdraw</className>
<asnTypeName>GPRSSubscriptionDataWithdraw</asnTypeName>
<moduleName>MAP_V9</moduleName>


<memberFunctions>

<memberFunctionSetChoice>
<name>SetChoiceAllGPRSData</name>
<signature>void SetChoiceAllGPRSData(AllGPRSData* choice)</signature>
<choiceName>AllGPRSData</choiceName>
<asnChoiceName>allGPRSData</asnChoiceName>
<choiceTypeName>AllGPRSData</choiceTypeName>
</memberFunctionSetChoice>

<memberFunctionSetChoiceWithRef>
<name>SetChoiceAllGPRSData</name>
<signature>void SetChoiceAllGPRSData(const AllGPRSData&amp; choice)</signature>
<choiceName>AllGPRSData</choiceName>
<asnChoiceName>allGPRSData</asnChoiceName>
<choiceTypeName>AllGPRSData</choiceTypeName>
</memberFunctionSetChoiceWithRef>

<memberFunctionGetChoice>
<name>GetChoiceAllGPRSData</name>
<signature>const AllGPRSData&amp; GetChoiceAllGPRSData() const</signature>
<choiceName>AllGPRSData</choiceName>
<asnChoiceName>allGPRSData</asnChoiceName>
<choiceTypeName>AllGPRSData</choiceTypeName>
</memberFunctionGetChoice>

<memberFunctionChoice>
<name>ChoiceAllGPRSData</name>
<signature>bool ChoiceAllGPRSData() const</signature>
<choiceName>AllGPRSData</choiceName>
<asnChoiceName>allGPRSData</asnChoiceName>
<choiceTypeName>AllGPRSData</choiceTypeName>
</memberFunctionChoice>

<memberFunctionSetChoice>
<name>SetChoiceContextIdList</name>
<signature>void SetChoiceContextIdList(ContextIdList* choice)</signature>
<choiceName>ContextIdList</choiceName>
<asnChoiceName>contextIdList</asnChoiceName>
<choiceTypeName>ContextIdList</choiceTypeName>
</memberFunctionSetChoice>

<memberFunctionSetChoiceWithRef>
<name>SetChoiceContextIdList</name>
<signature>void SetChoiceContextIdList(const ContextIdList&amp; choice)</signature>
<choiceName>ContextIdList</choiceName>
<asnChoiceName>contextIdList</asnChoiceName>
<choiceTypeName>ContextIdList</choiceTypeName>
</memberFunctionSetChoiceWithRef>

<memberFunctionGetChoice>
<name>GetChoiceContextIdList</name>
<signature>const ContextIdList&amp; GetChoiceContextIdList() const</signature>
<choiceName>ContextIdList</choiceName>
<asnChoiceName>contextIdList</asnChoiceName>
<choiceTypeName>ContextIdList</choiceTypeName>
</memberFunctionGetChoice>

<memberFunctionChoice>
<name>ChoiceContextIdList</name>
<signature>bool ChoiceContextIdList() const</signature>
<choiceName>ContextIdList</choiceName>
<asnChoiceName>contextIdList</asnChoiceName>
<choiceTypeName>ContextIdList</choiceTypeName>
</memberFunctionChoice>

</memberFunctions>



<asnDefinition>

<line>
<text></text>
</line>
<line>
<text>-- GPRSSubscriptionDataWithdraw information: </text>
</line>
<line>
<text>-- [not recursive]</text>
</line>
<line>
<text>-- [not exported]</text>
</line>
<line>
<text>-- [local reference counter = 1]</text>
</line>
<line>
<text>-- [import reference counter = 0]</text>
</line>
<line>
<text></text>
</line>
<line>
<text>GPRSSubscriptionDataWithdraw ::= CHOICE</text>
</line>
<line>
<text>{</text>
</line>
<line>
<text>    allGPRSData NULL,</text>
<shift></shift>
</line>
<line>
<text></text>
</line>
<line>
<text>    contextIdList ContextIdList -- [linked] --</text>
<shift></shift>
</line>
<line>
<text>}</text>
</line>
<line>
<text></text>
</line>
<line>
<text></text>
</line>

</asnDefinition>



</asnChoice>

</asnType>

