<?xml version="1.0"?>


<!--                                                                         -->
<!-- Generated by IntelliAsnCC ASN.1 compiler (C, C++, Java).                -->
<!--                                                                         -->
<!-- Do not edit!                                                            -->
<!--                                                                         -->
<!--                                                                         -->
<!-- (C) 2000, 2001 IntelliNet Technologies Inc. All Rights Reserved.        -->
<!--                                                                         -->
<!--                                                                         -->


<asnType>

<asnSequence>

<className>ODB_Data</className>
<asnTypeName>ODB-Data</asnTypeName>
<moduleName>MAP_V2</moduleName>


<memberFunctions>

<memberFunctionSet>
<name>SetOdb_GeneralData</name>
<signature>void SetOdb_GeneralData(ODB_GeneralData* element)</signature>
<elmentName>Odb_GeneralData</elmentName>
<asnElementName>odb-GeneralData</asnElementName>
<elementTypeName>ODB_GeneralData</elementTypeName>
<optional>no</optional>
</memberFunctionSet>

<memberFunctionSetWithRef>
<name>SetOdb_GeneralData</name>
<signature>void SetOdb_GeneralData(const ODB_GeneralData&amp; element)</signature>
<elementName>Odb_GeneralData</elementName>
<asnElementName>odb-GeneralData</asnElementName>
<elementTypeName>ODB_GeneralData</elementTypeName>
<optional>no</optional>
</memberFunctionSetWithRef>

<memberFunctionGet>
<name>GetOdb_GeneralData</name>
<signature>const ODB_GeneralData&amp; GetOdb_GeneralData() const</signature>
<elementName>Odb_GeneralData</elementName>
<asnElementName>odb-GeneralData</asnElementName>
<elementTypeName>ODB_GeneralData</elementTypeName>
<optional>no</optional>
</memberFunctionGet>

<memberFunctionSet>
<name>SetOdb_HPLMN_Data</name>
<signature>void SetOdb_HPLMN_Data(ODB_HPLMN_Data* element)</signature>
<elmentName>Odb_HPLMN_Data</elmentName>
<asnElementName>odb-HPLMN-Data</asnElementName>
<elementTypeName>ODB_HPLMN_Data</elementTypeName>
<optional>yes</optional>
</memberFunctionSet>

<memberFunctionSetWithRef>
<name>SetOdb_HPLMN_Data</name>
<signature>void SetOdb_HPLMN_Data(const ODB_HPLMN_Data&amp; element)</signature>
<elementName>Odb_HPLMN_Data</elementName>
<asnElementName>odb-HPLMN-Data</asnElementName>
<elementTypeName>ODB_HPLMN_Data</elementTypeName>
<optional>yes</optional>
</memberFunctionSetWithRef>

<memberFunctionGet>
<name>GetOdb_HPLMN_Data</name>
<signature>const ODB_HPLMN_Data&amp; GetOdb_HPLMN_Data() const</signature>
<elementName>Odb_HPLMN_Data</elementName>
<asnElementName>odb-HPLMN-Data</asnElementName>
<elementTypeName>ODB_HPLMN_Data</elementTypeName>
<optional>yes</optional>
</memberFunctionGet>

<memberFunctionOption>
<name>OptionOdb_HPLMN_Data</name>
<signature>bool OptionOdb_HPLMN_Data() const</signature>
<elementName>Odb_HPLMN_Data</elementName>
<asnElementName>odb-HPLMN-Data</asnElementName>
<elementTypeName>ODB_HPLMN_Data</elementTypeName>
</memberFunctionOption>

</memberFunctions>



<asnDefinition>

<line>
<text></text>
</line>
<line>
<text>-- ODB-Data information: </text>
</line>
<line>
<text>-- [not recursive]</text>
</line>
<line>
<text>-- [not exported]</text>
</line>
<line>
<text>-- [local reference counter = 1]</text>
</line>
<line>
<text>-- [import reference counter = 0]</text>
</line>
<line>
<text></text>
</line>
<line>
<text>ODB-Data ::= SEQUENCE</text>
</line>
<line>
<text>{</text>
</line>
<line>
<text>    odb-GeneralData ODB-GeneralData -- [linked] --,</text>
<shift></shift>
</line>
<line>
<text></text>
</line>
<line>
<text>    odb-HPLMN-Data ODB-HPLMN-Data -- [linked] -- OPTIONAL</text>
<shift></shift>
</line>
<line>
<text>}</text>
</line>
<line>
<text></text>
</line>
<line>
<text></text>
</line>

</asnDefinition>



</asnSequence>

</asnType>

